README.rst
setup.py
django_facebook_auth/__init__.py
django_facebook_auth/admin.py
django_facebook_auth/backends.py
django_facebook_auth/models.py
django_facebook_auth/tests.py
django_facebook_auth/views.py
django_facebook_auth_helper.egg-info/PKG-INFO
django_facebook_auth_helper.egg-info/SOURCES.txt
django_facebook_auth_helper.egg-info/dependency_links.txt
django_facebook_auth_helper.egg-info/requires.txt
django_facebook_auth_helper.egg-info/top_level.txt