Metadata-Version: 1.1
Name: django-facebook-auth-helper
Version: 0.1.6
Summary: Django implementation for Facebook authentication.
Home-page: https://github.com/pinetree408/django-facebook-auth
Author: Sangyoon Lee
Author-email: pinetree408@gmail.com
License: MIT License
Keywords: django facebook authentication
Platform: UNKNOWN
Classifier: Framework :: Django
Classifier: Intended Audience :: Developers
Classifier: License :: OSI Approved :: MIT License
Classifier: Operating System :: OS Independent
Classifier: Programming Language :: Python :: 2.7
Classifier: Topic :: Internet :: WWW/HTTP
